trytond/__init__.py
trytond/admin.py
trytond/application.py
trytond/bus.py
trytond/cache.py
trytond/commandline.py
trytond/config.py
trytond/console.py
trytond/const.py
trytond/convert.py
trytond/cron.py
trytond/exceptions.py
trytond/filestore.py
trytond/i18n.py
trytond/pool.py
trytond/pyson.py
trytond/rpc.py
trytond/security.py
trytond/sendmail.py
trytond/status.py
trytond/transaction.py
trytond/tryton.rnc
trytond/tryton.rng
trytond/url.py
trytond/worker.py
trytond/wsgi.py
trytond/backend/__init__.py
trytond/backend/database.py
trytond/backend/table.py
trytond/backend/postgresql/__init__.py
trytond/backend/postgresql/database.py
trytond/backend/postgresql/init.sql
trytond/backend/postgresql/table.py
trytond/backend/sqlite/__init__.py
trytond/backend/sqlite/database.py
trytond/backend/sqlite/init.sql
trytond/backend/sqlite/table.py
trytond/ir/__init__.py
trytond/ir/action.py
trytond/ir/action.xml
trytond/ir/attachment.py
trytond/ir/attachment.xml
trytond/ir/avatar.py
trytond/ir/cache.py
trytond/ir/calendar_.py
trytond/ir/calendar_.xml
trytond/ir/chat.py
trytond/ir/configuration.py
trytond/ir/cron.py
trytond/ir/cron.xml
trytond/ir/date.py
trytond/ir/email.xml
trytond/ir/email_.py
trytond/ir/error.py
trytond/ir/error.xml
trytond/ir/exceptions.py
trytond/ir/export.py
trytond/ir/export.xml
trytond/ir/ir.xml
trytond/ir/lang.py
trytond/ir/lang.xml
trytond/ir/message.py
trytond/ir/message.xml
trytond/ir/model.py
trytond/ir/model.xml
trytond/ir/module.py
trytond/ir/module.xml
trytond/ir/note.py
trytond/ir/note.xml
trytond/ir/queue.xml
trytond/ir/queue_.py
trytond/ir/resource.py
trytond/ir/routes.py
trytond/ir/rule.py
trytond/ir/rule.xml
trytond/ir/sequence.py
trytond/ir/sequence.xml
trytond/ir/session.py
trytond/ir/translation.py
trytond/ir/translation.xml
trytond/ir/trigger.py
trytond/ir/trigger.xml
trytond/ir/tryton.cfg
trytond/ir/fonts/karla.ttf
trytond/ir/locale/bg.po
trytond/ir/locale/ca.po
trytond/ir/locale/cs.po
trytond/ir/locale/de.po
trytond/ir/locale/es.po
trytond-7.8.4.dist-info/licenses/LICENSE
trytond-7.8.4.dist-info/METADATA
trytond-7.8.4.dist-info/WHEEL
trytond-7.8.4.dist-info/top_level.txt
trytond-7.8.4.dist-info/RECORD
